autoadsorbate/Neb.py
autoadsorbate/Particle.py
autoadsorbate/Smile.py
autoadsorbate/Surf.py
autoadsorbate/__init__.py
autoadsorbate/autoadsorbate.py
autoadsorbate/plotting.py
autoadsorbate/popneb.py
autoadsorbate/raster_utilities.py
autoadsorbate/string_utils.py
autoadsorbate/utils.py
autoadsorbate-0.2.5.dist-info/licenses/LICENSE
autoadsorbate-0.2.5.dist-info/METADATA
autoadsorbate-0.2.5.dist-info/WHEEL
autoadsorbate-0.2.5.dist-info/top_level.txt
autoadsorbate-0.2.5.dist-info/RECORD
