Metadata-Version: 2.4
Name: autoadsorbate
Version: 0.2.5
Summary: AutoAdsorbate is a lightweight and easy-to-use Python package for generating chemically meaningful configurations of molecules and fragments on surfaces. Built with minimal dependencies and a low barrier to entry, it enables rapid setup of surface-adsorbate systems using the Surrogate-SMILES (*SMILES) representation. Ideal for researchers in catalysis, nanotech, and materials science, AutoAdsorbate streamlines dataset generation for simulations and machine learning workflows.
Author-email: Edvin Fako <edvinfako@gmail.com>
License-Expression: MIT
Requires-Python: >=3.9
License-File: LICENSE
Requires-Dist: ase>=3.24.0
Requires-Dist: pandas>=2.0.0
Requires-Dist: rdkit>=2022.9.5
Dynamic: license-file
